equityanalyst/__init__.py
equityanalyst/__main__.py
equityanalyst/setup.py
Equity_Analyst-1.0.2.dist-info/LICENSE.txt
Equity_Analyst-1.0.2.dist-info/METADATA
Equity_Analyst-1.0.2.dist-info/WHEEL
Equity_Analyst-1.0.2.dist-info/top_level.txt
Equity_Analyst-1.0.2.dist-info/RECORD
