Metadata-Version: 2.1
Name: Equity-Analyst
Version: 1.0.2
Summary: Equity Analyst is an Open-Source Python package with the key function of accepting the ticker name of the stock and predicting its future value based on historical data.
Home-page: https://github.com/harshitbhavnani/Equity-Analyst
Author: Harshit Bhavnani
Author-email: harshit.bhavnani@gmail.com
License: MIT
Platform: UNKNOWN
